MANIFEST.in
README.md
setup.py
cmsplugin_fbgallery/__init__.py
cmsplugin_fbgallery/admin.py
cmsplugin_fbgallery/cms_plugins.py
cmsplugin_fbgallery/facebook.py
cmsplugin_fbgallery/models.py
cmsplugin_fbgallery/tests.py
cmsplugin_fbgallery/views.py
cmsplugin_fbgallery.egg-info/PKG-INFO
cmsplugin_fbgallery.egg-info/SOURCES.txt
cmsplugin_fbgallery.egg-info/dependency_links.txt
cmsplugin_fbgallery.egg-info/not-zip-safe
cmsplugin_fbgallery.egg-info/top_level.txt
cmsplugin_fbgallery/migrations/0001_initial.py
cmsplugin_fbgallery/migrations/0001_initial.pyc
cmsplugin_fbgallery/migrations/0002_rename_table.py
cmsplugin_fbgallery/migrations/0002_rename_table.pyc
cmsplugin_fbgallery/migrations/__init__.py
cmsplugin_fbgallery/migrations/__init__.pyc
cmsplugin_fbgallery/templates/cmsplugin_fbgallery/album.html