Metadata-Version: 1.0
Name: cmsplugin-fbgallery
Version: 1.1.0
Summary: facebook gallery plugin for django-cms
Home-page: https://github.com/changer/cmsplugin-fbgallery.git
Author: Vinit Kumar
Author-email: vinit.kumar@changer.nl
License: MIT
Platform: UNKNOWN
